xsectron/__init__.py
xsectron/literatures.py
xsectron/utils.py
xsectron/xsec.py
xsectron-0.0.0.dist-info/LICENSE
xsectron-0.0.0.dist-info/METADATA
xsectron-0.0.0.dist-info/WHEEL
xsectron-0.0.0.dist-info/top_level.txt
xsectron-0.0.0.dist-info/RECORD
